README.md
setup.py
tic_tac_toe/__init__.py
tic_tac_toe/tic_tac_toe.py
tic_tac_toe_jf.egg-info/PKG-INFO
tic_tac_toe_jf.egg-info/SOURCES.txt
tic_tac_toe_jf.egg-info/dependency_links.txt
tic_tac_toe_jf.egg-info/not-zip-safe
tic_tac_toe_jf.egg-info/top_level.txt