Metadata-Version: 1.0
Name: tic-tac-toe-jf
Version: 0.2
Summary: Tic-tac-toe game
Home-page: UNKNOWN
Author: UNKNOWN
Author-email: UNKNOWN
License: UNKNOWN
Platform: UNKNOWN
